{
  "timestamp": "2026-03-06 10:58:03",
  "total_stocks": 8,
  "results": [
    {
      "recommendation": "BUY",
      "confidence": "LOW",
      "entry": 800,
      "stop": 780.0,
      "target": 824.0,
      "rr": "3:1",
      "reasons": [
        "AI analysis (text parse)"
      ],
      "warnings": [],
      "stock_name": "MiniMax Group, Inc",
      "market_bias": "BULLISH",
      "trend_strength": "STRONG_BULLISH",
      "pattern_type": "NONE",
      "key_support": 0,
      "key_resistance": 0,
      "analysis": {
        "price": 800,
        "ema20": 794.4,
        "ema50": 794.4,
        "ema200": 794.4,
        "rsi": 79.48717948717949,
        "atr": 39.166666666666664,
        "vwap": 834.4534469159172,
        "macd": {
          "macd": 0,
          "signal": 0,
          "histogram": 0,
          "trend": "NEUTRAL"
        },
        "bollinger": {
          "upper": 0,
          "middle": 0,
          "lower": 0,
          "bandwidth": 0,
          "position": 0
        },
        "stochastic": {
          "k": 50,
          "d": 50,
          "zone": "NEUTRAL"
        },
        "pivot": {
          "pivot": 817.1666666666666,
          "r1": 856.3333333333333,
          "r2": 879.1666666666666,
          "s1": 794.3333333333333,
          "s2": 755.1666666666666
        },
        "patterns": {
          "pattern": "NONE",
          "signal": "NEUTRAL",
          "volume_spike": false
        },
        "change_pct": -0.7798440311937612
      },
      "news": [],
      "sentiment": 0.0,
      "atr_pct": 4.9,
      "vwap_distance": 4.31,
      "ai_recommendation": {
        "recommendation": "BUY",
        "confidence": "LOW",
        "reasons": [
          "AI analysis (text parse)"
        ],
        "warnings": [],
        "entry_price": 800,
        "stop_loss": 780.0,
        "target_price": 824.0,
        "risk_reward": "3:1"
      },
      "ai_sentiment": 0.0,
      "code": "100",
      "timestamp": "2026-03-06 10:47:15"
    },
    {
      "recommendation": "HOLD",
      "confidence": "LOW",
      "entry": 6.36,
      "stop": 6.2,
      "target": 6.55,
      "rr": "3:1",
      "reasons": [
        "AI analysis (text parse)"
      ],
      "warnings": [
        "Price only 0.1% from VWAP"
      ],
      "stock_name": "\u5de5\u5546\u9280\u884c",
      "market_bias": "BEARISH",
      "trend_strength": "MODERATE",
      "pattern_type": "NONE",
      "key_support": 6.38,
      "key_resistance": 6.38,
      "analysis": {
        "price": 6.36,
        "ema20": 6.377,
        "ema50": 6.377,
        "ema200": 6.377,
        "rsi": 61.53846153846165,
        "atr": 0.05777777777777783,
        "vwap": 6.368337165808192,
        "macd": {
          "macd": 0,
          "signal": 0,
          "histogram": 0,
          "trend": "NEUTRAL"
        },
        "bollinger": {
          "upper": 0,
          "middle": 0,
          "lower": 0,
          "bandwidth": 0,
          "position": 0
        },
        "stochastic": {
          "k": 50,
          "d": 50,
          "zone": "NEUTRAL"
        },
        "pivot": {
          "pivot": 6.383333333333334,
          "r1": 6.406666666666667,
          "r2": 6.443333333333333,
          "s1": 6.346666666666668,
          "s2": 6.323333333333334
        },
        "patterns": {
          "pattern": "NONE",
          "signal": "NEUTRAL",
          "volume_spike": false
        },
        "change_pct": 0.47095761381476053
      },
      "news": [],
      "sentiment": 0.0,
      "atr_pct": 0.91,
      "vwap_distance": 0.13,
      "ai_recommendation": {
        "recommendation": "HOLD",
        "confidence": "LOW",
        "reasons": [
          "AI analysis (text parse)"
        ],
        "warnings": [],
        "entry_price": 6.36,
        "stop_loss": 6.2,
        "target_price": 6.55,
        "risk_reward": "3:1"
      },
      "ai_sentiment": 0.0,
      "code": "1398",
      "timestamp": "2026-03-06 10:48:35"
    },
    {
      "recommendation": "HOLD",
      "confidence": "LOW",
      "entry": 96.95,
      "stop": 94.53,
      "target": 99.86,
      "rr": "3:1",
      "reasons": [
        "AI analysis (text parse)"
      ],
      "warnings": [],
      "stock_name": "\u4eac\u6771\u96c6\u5718\uff0d\uff33\uff37",
      "market_bias": "BEARISH",
      "trend_strength": "STRONG_BEARISH",
      "pattern_type": "NONE",
      "key_support": 0,
      "key_resistance": 0,
      "analysis": {
        "price": 96.95,
        "ema20": 98.64500000000001,
        "ema50": 98.64500000000001,
        "ema200": 98.64500000000001,
        "rsi": 79.90196078431373,
        "atr": 1.683333333333331,
        "vwap": 103.71910858813612,
        "macd": {
          "macd": 0,
          "signal": 0,
          "histogram": 0,
          "trend": "NEUTRAL"
        },
        "bollinger": {
          "upper": 0,
          "middle": 0,
          "lower": 0,
          "bandwidth": 0,
          "position": 0
        },
        "stochastic": {
          "k": 50,
          "d": 50,
          "zone": "NEUTRAL"
        },
        "pivot": {
          "pivot": 101.13333333333333,
          "r1": 103.76666666666665,
          "r2": 105.23333333333332,
          "s1": 99.66666666666666,
          "s2": 97.03333333333333
        },
        "patterns": {
          "pattern": "VOLUME_SPIKE_BULL",
          "signal": "NEUTRAL",
          "volume_spike": true
        },
        "change_pct": 1.7595307917888536
      },
      "news": [],
      "sentiment": 0.0,
      "atr_pct": 1.74,
      "vwap_distance": 6.98,
      "ai_recommendation": {
        "recommendation": "HOLD",
        "confidence": "LOW",
        "reasons": [
          "AI analysis (text parse)"
        ],
        "warnings": [],
        "entry_price": 96.95,
        "stop_loss": 94.53,
        "target_price": 99.86,
        "risk_reward": "3:1"
      },
      "ai_sentiment": 0.0,
      "code": "9618",
      "timestamp": "2026-03-06 10:50:31"
    },
    {
      "recommendation": "BUY",
      "confidence": "HIGH",
      "entry": 35.28,
      "stop": 34.4,
      "target": 36.34,
      "rr": "3:1",
      "reasons": [
        "AI analysis (text parse)"
      ],
      "warnings": [],
      "stock_name": "\u6c7d\u8eca\u4e4b\u5bb6\uff0d\uff33",
      "market_bias": "BEARISH",
      "trend_strength": "MODERATE",
      "pattern_type": "NONE",
      "key_support": 35.45,
      "key_resistance": 35.45,
      "analysis": {
        "price": 35.28,
        "ema20": 35.454,
        "ema50": 35.454,
        "ema200": 35.454,
        "rsi": 39.024390243902396,
        "atr": 0.5555555555555564,
        "vwap": 35.98078717201167,
        "macd": {
          "macd": 0,
          "signal": 0,
          "histogram": 0,
          "trend": "NEUTRAL"
        },
        "bollinger": {
          "upper": 0,
          "middle": 0,
          "lower": 0,
          "bandwidth": 0,
          "position": 0
        },
        "stochastic": {
          "k": 50,
          "d": 50,
          "zone": "NEUTRAL"
        },
        "pivot": {
          "pivot": 36.50000000000001,
          "r1": 36.62000000000001,
          "r2": 36.82000000000001,
          "s1": 36.30000000000001,
          "s2": 36.18000000000001
        },
        "patterns": {
          "pattern": "VOLUME_SPIKE_BEAR",
          "signal": "NEUTRAL",
          "volume_spike": true
        },
        "change_pct": -3.0752333882482272
      },
      "news": [],
      "sentiment": 0.0,
      "atr_pct": 1.57,
      "vwap_distance": 1.99,
      "ai_recommendation": {
        "recommendation": "BUY",
        "confidence": "HIGH",
        "reasons": [
          "AI analysis (text parse)"
        ],
        "warnings": [],
        "entry_price": 35.28,
        "stop_loss": 34.4,
        "target_price": 36.34,
        "risk_reward": "3:1"
      },
      "ai_sentiment": 0.0,
      "code": "2518",
      "timestamp": "2026-03-06 10:51:55"
    },
    {
      "recommendation": "BUY",
      "confidence": "LOW",
      "entry": 0.74,
      "stop": 0.72,
      "target": 0.76,
      "rr": "3:1",
      "reasons": [
        "AI analysis (text parse)"
      ],
      "warnings": [],
      "stock_name": "\u806f\u5408\u80fd\u6e90\u96c6\u5718",
      "market_bias": "BEARISH",
      "trend_strength": "MODERATE",
      "pattern_type": "NONE",
      "key_support": 0.77,
      "key_resistance": 0.77,
      "analysis": {
        "price": 0.74,
        "ema20": 0.7699999999999999,
        "ema50": 0.7699999999999999,
        "ema200": 0.7699999999999999,
        "rsi": 42.857142857142854,
        "atr": 0.03888888888888891,
        "vwap": 0.7659794093741532,
        "macd": {
          "macd": 0,
          "signal": 0,
          "histogram": 0,
          "trend": "NEUTRAL"
        },
        "bollinger": {
          "upper": 0,
          "middle": 0,
          "lower": 0,
          "bandwidth": 0,
          "position": 0
        },
        "stochastic": {
          "k": 50,
          "d": 50,
          "zone": "NEUTRAL"
        },
        "pivot": {
          "pivot": 0.7600000000000001,
          "r1": 0.7800000000000002,
          "r2": 0.8000000000000002,
          "s1": 0.7400000000000002,
          "s2": 0.7200000000000001
        },
        "patterns": {
          "pattern": "NONE",
          "signal": "NEUTRAL",
          "volume_spike": false
        },
        "change_pct": 1.3157894736842117
      },
      "news": [],
      "sentiment": 0.0,
      "atr_pct": 5.26,
      "vwap_distance": 3.51,
      "ai_recommendation": {
        "recommendation": "BUY",
        "confidence": "LOW",
        "reasons": [
          "AI analysis (text parse)"
        ],
        "warnings": [],
        "entry_price": 0.74,
        "stop_loss": 0.72,
        "target_price": 0.76,
        "risk_reward": "3:1"
      },
      "ai_sentiment": 0.0,
      "code": "467",
      "timestamp": "2026-03-06 10:53:13"
    },
    {
      "recommendation": "BUY",
      "confidence": "LOW",
      "entry": 0.56,
      "stop": 0.55,
      "target": 0.58,
      "rr": "3:1",
      "reasons": [
        "AI analysis (text parse)"
      ],
      "warnings": [],
      "stock_name": "\u4e2d\u4fe1\u8cc7\u6e90",
      "market_bias": "BULLISH",
      "trend_strength": "STRONG_BULLISH",
      "pattern_type": "NONE",
      "key_support": 0.55,
      "key_resistance": 0.55,
      "analysis": {
        "price": 0.56,
        "ema20": 0.554,
        "ema50": 0.554,
        "ema200": 0.554,
        "rsi": 56.24999999999998,
        "atr": 0.024444444444444418,
        "vwap": 0.5810757269940942,
        "macd": {
          "macd": 0,
          "signal": 0,
          "histogram": 0,
          "trend": "NEUTRAL"
        },
        "bollinger": {
          "upper": 0,
          "middle": 0,
          "lower": 0,
          "bandwidth": 0,
          "position": 0
        },
        "stochastic": {
          "k": 50,
          "d": 50,
          "zone": "NEUTRAL"
        },
        "pivot": {
          "pivot": 0.59,
          "r1": 0.61,
          "r2": 0.63,
          "s1": 0.57,
          "s2": 0.5499999999999999
        },
        "patterns": {
          "pattern": "NONE",
          "signal": "NEUTRAL",
          "volume_spike": false
        },
        "change_pct": -1.6949152542372898
      },
      "news": [],
      "sentiment": 0.0,
      "atr_pct": 4.37,
      "vwap_distance": 3.76,
      "ai_recommendation": {
        "recommendation": "BUY",
        "confidence": "LOW",
        "reasons": [
          "AI analysis (text parse)"
        ],
        "warnings": [],
        "entry_price": 0.56,
        "stop_loss": 0.55,
        "target_price": 0.58,
        "risk_reward": "3:1"
      },
      "ai_sentiment": 0.0,
      "code": "1205",
      "timestamp": "2026-03-06 10:54:41"
    },
    {
      "recommendation": "SELL",
      "confidence": "LOW",
      "entry": 15.16,
      "stop": 14.78,
      "target": 15.61,
      "rr": "3:1",
      "reasons": [
        "AI analysis (text parse)"
      ],
      "warnings": [],
      "stock_name": "\u5409\u5229\u6c7d\u8eca",
      "market_bias": "BEARISH",
      "trend_strength": "STRONG_BEARISH",
      "pattern_type": "NONE",
      "key_support": 0,
      "key_resistance": 0,
      "analysis": {
        "price": 15.16,
        "ema20": 15.338999999999999,
        "ema50": 15.338999999999999,
        "ema200": 15.338999999999999,
        "rsi": 74.1379310344827,
        "atr": 0.22555555555555568,
        "vwap": 15.678875791955209,
        "macd": {
          "macd": 0,
          "signal": 0,
          "histogram": 0,
          "trend": "NEUTRAL"
        },
        "bollinger": {
          "upper": 0,
          "middle": 0,
          "lower": 0,
          "bandwidth": 0,
          "position": 0
        },
        "stochastic": {
          "k": 50,
          "d": 50,
          "zone": "NEUTRAL"
        },
        "pivot": {
          "pivot": 15.453333333333333,
          "r1": 15.746666666666666,
          "r2": 15.923333333333334,
          "s1": 15.276666666666666,
          "s2": 14.983333333333333
        },
        "patterns": {
          "pattern": "VOLUME_SPIKE_BULL",
          "signal": "NEUTRAL",
          "volume_spike": true
        },
        "change_pct": 0.7707129094412281
      },
      "news": [],
      "sentiment": 0.0,
      "atr_pct": 1.49,
      "vwap_distance": 3.42,
      "ai_recommendation": {
        "recommendation": "SELL",
        "confidence": "LOW",
        "reasons": [
          "AI analysis (text parse)"
        ],
        "warnings": [],
        "entry_price": 15.16,
        "stop_loss": 14.78,
        "target_price": 15.61,
        "risk_reward": "3:1"
      },
      "ai_sentiment": 0.0,
      "code": "175",
      "timestamp": "2026-03-06 10:56:05"
    },
    {
      "recommendation": "HOLD",
      "confidence": "LOW",
      "entry": 520,
      "stop": 507.0,
      "target": 535.6,
      "rr": "3:1",
      "reasons": [
        "AI analysis (text parse)"
      ],
      "warnings": [],
      "stock_name": "\u667a\u8b5c",
      "market_bias": "BULLISH",
      "trend_strength": "STRONG_BULLISH",
      "pattern_type": "MOMENTUM",
      "key_support": 519.65,
      "key_resistance": 519.65,
      "analysis": {
        "price": 520,
        "ema20": 519.65,
        "ema50": 519.65,
        "ema200": 519.65,
        "rsi": 62.63157894736842,
        "atr": 22.22222222222222,
        "vwap": 546.4520648967551,
        "macd": {
          "macd": 0,
          "signal": 0,
          "histogram": 0,
          "trend": "NEUTRAL"
        },
        "bollinger": {
          "upper": 0,
          "middle": 0,
          "lower": 0,
          "bandwidth": 0,
          "position": 0
        },
        "stochastic": {
          "k": 50,
          "d": 50,
          "zone": "NEUTRAL"
        },
        "pivot": {
          "pivot": 530.3333333333334,
          "r1": 555.6666666666667,
          "r2": 570.3333333333334,
          "s1": 515.6666666666667,
          "s2": 490.33333333333337
        },
        "patterns": {
          "pattern": "SHOOTING_STAR,VOLUME_SPIKE_BEAR",
          "signal": "BEARISH",
          "volume_spike": true
        },
        "change_pct": -1.2939001848428837
      },
      "news": [],
      "sentiment": 0.0,
      "atr_pct": 4.27,
      "vwap_distance": 5.09,
      "ai_recommendation": {
        "recommendation": "HOLD",
        "confidence": "LOW",
        "reasons": [
          "AI analysis (text parse)"
        ],
        "warnings": [],
        "entry_price": 520,
        "stop_loss": 507.0,
        "target_price": 535.6,
        "risk_reward": "3:1"
      },
      "ai_sentiment": 0.0,
      "code": "2513",
      "timestamp": "2026-03-06 10:58:03"
    }
  ]
}