{
  "timestamp": "2026-03-09 22:16:28",
  "total_stocks": 10,
  "results": [
    {
      "recommendation": "HOLD",
      "confidence": "LOW",
      "entry": 0,
      "stop": 0.0,
      "target": 0.0,
      "rr": "3:1",
      "reasons": [
        "AI analysis (text parse)"
      ],
      "warnings": [
        "Ticker unavailable or no data"
      ],
      "stock_name": "SPDR S&P 500 ETF",
      "market_bias": "BEARISH",
      "analysis": {},
      "news": [],
      "sentiment": 0.0,
      "trend_strength": "WEAK",
      "pattern_type": "NONE",
      "ai_recommendation": {
        "recommendation": "HOLD",
        "confidence": "LOW",
        "reasons": [
          "AI analysis (text parse)"
        ],
        "warnings": [],
        "entry_price": 0,
        "stop_loss": 0.0,
        "target_price": 0.0,
        "risk_reward": "3:1"
      },
      "ai_sentiment": 0.0,
      "code": "SPY",
      "timestamp": "2026-03-09 22:02:08"
    },
    {
      "recommendation": "HOLD",
      "confidence": "LOW",
      "entry": 0,
      "stop": 0.0,
      "target": 0.0,
      "rr": "3:1",
      "reasons": [
        "AI analysis (text parse)"
      ],
      "warnings": [
        "Ticker unavailable or no data"
      ],
      "stock_name": "Invesco QQQ Trust",
      "market_bias": "BEARISH",
      "analysis": {},
      "news": [],
      "sentiment": 0.0,
      "trend_strength": "WEAK",
      "pattern_type": "NONE",
      "ai_recommendation": {
        "recommendation": "HOLD",
        "confidence": "LOW",
        "reasons": [
          "AI analysis (text parse)"
        ],
        "warnings": [],
        "entry_price": 0,
        "stop_loss": 0.0,
        "target_price": 0.0,
        "risk_reward": "3:1"
      },
      "ai_sentiment": 0.0,
      "code": "QQQ",
      "timestamp": "2026-03-09 22:03:32"
    },
    {
      "recommendation": "HOLD",
      "confidence": "LOW",
      "entry": 183.34,
      "stop": 178.76,
      "target": 188.84,
      "rr": "3:1",
      "reasons": [
        "AI analysis (text parse)"
      ],
      "warnings": [],
      "stock_name": "NVIDIA Corporation",
      "market_bias": "BULLISH",
      "trend_strength": "MODERATE",
      "pattern_type": "NONE",
      "key_support": 176.98,
      "key_resistance": 176.98,
      "analysis": {
        "price": 183.34,
        "ema20": 176.9789,
        "ema50": 176.9789,
        "ema200": 176.9789,
        "rsi": 46.41605606881182,
        "atr": 1.649222222222221,
        "vwap": 176.74383767154168,
        "macd": {
          "macd": 0,
          "signal": 0,
          "histogram": 0,
          "trend": "NEUTRAL"
        },
        "bollinger": {
          "upper": 0,
          "middle": 0,
          "lower": 0,
          "bandwidth": 0,
          "position": 0
        },
        "stochastic": {
          "k": 50,
          "d": 50,
          "zone": "NEUTRAL"
        },
        "pivot": {
          "pivot": 176.88433333333333,
          "r1": 178.20866666666666,
          "r2": 179.48233333333332,
          "s1": 175.61066666666667,
          "s2": 174.28633333333335
        },
        "patterns": {
          "pattern": "NONE",
          "signal": "NEUTRAL",
          "volume_spike": false
        },
        "change_pct": 0.3532370644586995
      },
      "news": [],
      "sentiment": 0.0,
      "atr_pct": 0.9,
      "vwap_distance": 3.6,
      "ai_recommendation": {
        "recommendation": "HOLD",
        "confidence": "LOW",
        "reasons": [
          "AI analysis (text parse)"
        ],
        "warnings": [],
        "entry_price": 183.34,
        "stop_loss": 178.76,
        "target_price": 188.84,
        "risk_reward": "3:1"
      },
      "ai_sentiment": 0.0,
      "code": "NVDA",
      "timestamp": "2026-03-09 22:05:24"
    },
    {
      "recommendation": "HOLD",
      "confidence": "LOW",
      "entry": 405.55,
      "stop": 395.41,
      "target": 417.72,
      "rr": "3:1",
      "reasons": [
        "AI analysis (text parse)"
      ],
      "warnings": [],
      "stock_name": "Tesla, Inc.",
      "market_bias": "BULLISH",
      "trend_strength": "STRONG_BULLISH",
      "pattern_type": "NONE",
      "key_support": 0,
      "key_resistance": 0,
      "analysis": {
        "price": 405.55,
        "ema20": 391.06489999999997,
        "ema50": 391.06489999999997,
        "ema200": 391.06489999999997,
        "rsi": 25.294497738456144,
        "atr": 4.228777777777775,
        "vwap": 386.6830974825491,
        "macd": {
          "macd": 0,
          "signal": 0,
          "histogram": 0,
          "trend": "NEUTRAL"
        },
        "bollinger": {
          "upper": 0,
          "middle": 0,
          "lower": 0,
          "bandwidth": 0,
          "position": 0
        },
        "stochastic": {
          "k": 50,
          "d": 50,
          "zone": "NEUTRAL"
        },
        "pivot": {
          "pivot": 386.8633333333333,
          "r1": 390.68666666666655,
          "r2": 396.8133333333333,
          "s1": 380.73666666666657,
          "s2": 376.9133333333333
        },
        "patterns": {
          "pattern": "NONE",
          "signal": "NEUTRAL",
          "volume_spike": false
        },
        "change_pct": 0.3507905138339894
      },
      "news": [],
      "sentiment": 0.0,
      "atr_pct": 1.04,
      "vwap_distance": 4.65,
      "ai_recommendation": {
        "recommendation": "HOLD",
        "confidence": "LOW",
        "reasons": [
          "AI analysis (text parse)"
        ],
        "warnings": [],
        "entry_price": 405.55,
        "stop_loss": 395.41,
        "target_price": 417.72,
        "risk_reward": "3:1"
      },
      "ai_sentiment": 0.0,
      "code": "TSLA",
      "timestamp": "2026-03-09 22:07:18"
    },
    {
      "recommendation": "HOLD",
      "confidence": "LOW",
      "entry": 410.68,
      "stop": 400.41,
      "target": 423.0,
      "rr": "3:1",
      "reasons": [
        "AI analysis (text parse)"
      ],
      "warnings": [],
      "stock_name": "Microsoft Corporation",
      "market_bias": "BULLISH",
      "trend_strength": "STRONG_BULLISH",
      "pattern_type": "NONE",
      "key_support": 0,
      "key_resistance": 0,
      "analysis": {
        "price": 410.68,
        "ema20": 405.5539,
        "ema50": 405.5539,
        "ema200": 405.5539,
        "rsi": 35.52511415525106,
        "atr": 3.0022222222222266,
        "vwap": 405.4508679346951,
        "macd": {
          "macd": 0,
          "signal": 0,
          "histogram": 0,
          "trend": "NEUTRAL"
        },
        "bollinger": {
          "upper": 0,
          "middle": 0,
          "lower": 0,
          "bandwidth": 0,
          "position": 0
        },
        "stochastic": {
          "k": 50,
          "d": 50,
          "zone": "NEUTRAL"
        },
        "pivot": {
          "pivot": 405.49666666666667,
          "r1": 408.53333333333336,
          "r2": 411.5366666666667,
          "s1": 402.49333333333334,
          "s2": 399.45666666666665
        },
        "patterns": {
          "pattern": "NONE",
          "signal": "NEUTRAL",
          "volume_spike": false
        },
        "change_pct": -0.01972727048553352
      },
      "news": [],
      "sentiment": 0.0,
      "atr_pct": 0.73,
      "vwap_distance": 1.27,
      "ai_recommendation": {
        "recommendation": "HOLD",
        "confidence": "LOW",
        "reasons": [
          "AI analysis (text parse)"
        ],
        "warnings": [],
        "entry_price": 410.68,
        "stop_loss": 400.41,
        "target_price": 423.0,
        "risk_reward": "3:1"
      },
      "ai_sentiment": 0.0,
      "code": "MSFT",
      "timestamp": "2026-03-09 22:09:17"
    },
    {
      "recommendation": "BUY",
      "confidence": "LOW",
      "entry": 218.94,
      "stop": 213.47,
      "target": 225.51,
      "rr": "3:1",
      "reasons": [
        "AI analysis (text parse)"
      ],
      "warnings": [],
      "stock_name": "Amazon.com, Inc.",
      "market_bias": "BULLISH",
      "trend_strength": "STRONG_BULLISH",
      "pattern_type": "BREAKOUT",
      "key_support": 0,
      "key_resistance": 0,
      "analysis": {
        "price": 218.94,
        "ema20": 210.27800000000002,
        "ema50": 210.27800000000002,
        "ema200": 210.27800000000002,
        "rsi": 21.468298109010064,
        "atr": 2.426555555555549,
        "vwap": 208.85313757337707,
        "macd": {
          "macd": 0,
          "signal": 0,
          "histogram": 0,
          "trend": "NEUTRAL"
        },
        "bollinger": {
          "upper": 0,
          "middle": 0,
          "lower": 0,
          "bandwidth": 0,
          "position": 0
        },
        "stochastic": {
          "k": 50,
          "d": 50,
          "zone": "NEUTRAL"
        },
        "pivot": {
          "pivot": 209.045,
          "r1": 210.71999999999997,
          "r2": 213.96999999999997,
          "s1": 205.795,
          "s2": 204.12
        },
        "patterns": {
          "pattern": "SHOOTING_STAR",
          "signal": "BEARISH",
          "volume_spike": false
        },
        "change_pct": 0.19279895888562476
      },
      "news": [],
      "sentiment": 0.0,
      "atr_pct": 1.11,
      "vwap_distance": 4.61,
      "ai_recommendation": {
        "recommendation": "BUY",
        "confidence": "LOW",
        "reasons": [
          "AI analysis (text parse)"
        ],
        "warnings": [],
        "entry_price": 218.94,
        "stop_loss": 213.47,
        "target_price": 225.51,
        "risk_reward": "3:1"
      },
      "ai_sentiment": 0.0,
      "code": "AMZN",
      "timestamp": "2026-03-09 22:10:44"
    },
    {
      "recommendation": "BUY",
      "confidence": "LOW",
      "entry": 660.57,
      "stop": 644.06,
      "target": 680.39,
      "rr": "3:1",
      "reasons": [
        "AI analysis (text parse)"
      ],
      "warnings": [],
      "stock_name": "Meta Platforms, Inc.",
      "market_bias": "BULLISH",
      "trend_strength": "STRONG_BULLISH",
      "pattern_type": "NONE",
      "key_support": 0,
      "key_resistance": 0,
      "analysis": {
        "price": 660.57,
        "ema20": 636.6025999999999,
        "ema50": 636.6025999999999,
        "ema200": 636.6025999999999,
        "rsi": 13.82289416846632,
        "atr": 4.65333333333332,
        "vwap": 630.990760070068,
        "macd": {
          "macd": 0,
          "signal": 0,
          "histogram": 0,
          "trend": "NEUTRAL"
        },
        "bollinger": {
          "upper": 0,
          "middle": 0,
          "lower": 0,
          "bandwidth": 0,
          "position": 0
        },
        "stochastic": {
          "k": 50,
          "d": 50,
          "zone": "NEUTRAL"
        },
        "pivot": {
          "pivot": 631.1963333333333,
          "r1": 635.6126666666667,
          "r2": 642.1053333333333,
          "s1": 624.7036666666667,
          "s2": 620.2873333333333
        },
        "patterns": {
          "pattern": "NONE",
          "signal": "NEUTRAL",
          "volume_spike": false
        },
        "change_pct": -0.019074262461852197
      },
      "news": [],
      "sentiment": 0.0,
      "atr_pct": 0.7,
      "vwap_distance": 4.48,
      "ai_recommendation": {
        "recommendation": "BUY",
        "confidence": "LOW",
        "reasons": [
          "AI analysis (text parse)"
        ],
        "warnings": [],
        "entry_price": 660.57,
        "stop_loss": 644.06,
        "target_price": 680.39,
        "risk_reward": "3:1"
      },
      "ai_sentiment": 0.0,
      "code": "META",
      "timestamp": "2026-03-09 22:12:15"
    },
    {
      "recommendation": "BUY",
      "confidence": "HIGH",
      "entry": 152.67,
      "stop": 148.85,
      "target": 157.25,
      "rr": "3:1",
      "reasons": [
        "AI analysis (text parse)"
      ],
      "warnings": [],
      "stock_name": "Palantir Technologies Inc.",
      "market_bias": "BEARISH",
      "trend_strength": "STRONG_BEARISH",
      "pattern_type": "MOMENTUM",
      "key_support": 155.29,
      "key_resistance": 155.29,
      "analysis": {
        "price": 152.67,
        "ema20": 155.2894,
        "ema50": 155.2894,
        "ema200": 155.2894,
        "rsi": 30.49111178065681,
        "atr": 2.0309999999999997,
        "vwap": 155.50145816328111,
        "macd": {
          "macd": 0,
          "signal": 0,
          "histogram": 0,
          "trend": "NEUTRAL"
        },
        "bollinger": {
          "upper": 0,
          "middle": 0,
          "lower": 0,
          "bandwidth": 0,
          "position": 0
        },
        "stochastic": {
          "k": 50,
          "d": 50,
          "zone": "NEUTRAL"
        },
        "pivot": {
          "pivot": 155.75333333333333,
          "r1": 157.24666666666667,
          "r2": 159.93333333333334,
          "s1": 153.06666666666666,
          "s2": 151.57333333333332
        },
        "patterns": {
          "pattern": "SHOOTING_STAR,EVENING_STAR,VOLUME_SPIKE_BEAR",
          "signal": "BEARISH",
          "volume_spike": true
        },
        "change_pct": -0.3170289855072522
      },
      "news": [],
      "sentiment": 0.0,
      "atr_pct": 1.33,
      "vwap_distance": 1.85,
      "ai_recommendation": {
        "recommendation": "BUY",
        "confidence": "HIGH",
        "reasons": [
          "AI analysis (text parse)"
        ],
        "warnings": [],
        "entry_price": 152.67,
        "stop_loss": 148.85,
        "target_price": 157.25,
        "risk_reward": "3:1"
      },
      "ai_sentiment": 0.0,
      "code": "PLTR",
      "timestamp": "2026-03-09 22:13:46"
    },
    {
      "recommendation": "HOLD",
      "confidence": "LOW",
      "entry": 300.88,
      "stop": 293.36,
      "target": 309.91,
      "rr": "3:1",
      "reasons": [
        "AI analysis (text parse)"
      ],
      "warnings": [],
      "stock_name": "Alphabet Inc.",
      "market_bias": "BULLISH",
      "trend_strength": "MODERATE",
      "pattern_type": "NONE",
      "key_support": 295.19,
      "key_resistance": 295.19,
      "analysis": {
        "price": 300.88,
        "ema20": 295.1949,
        "ema50": 295.1949,
        "ema200": 295.1949,
        "rsi": 41.270005162622745,
        "atr": 2.566444444444452,
        "vwap": 295.7389097457037,
        "macd": {
          "macd": 0,
          "signal": 0,
          "histogram": 0,
          "trend": "NEUTRAL"
        },
        "bollinger": {
          "upper": 0,
          "middle": 0,
          "lower": 0,
          "bandwidth": 0,
          "position": 0
        },
        "stochastic": {
          "k": 50,
          "d": 50,
          "zone": "NEUTRAL"
        },
        "pivot": {
          "pivot": 294.96,
          "r1": 297.11999999999995,
          "r2": 298.96,
          "s1": 293.11999999999995,
          "s2": 290.96
        },
        "patterns": {
          "pattern": "NONE",
          "signal": "NEUTRAL",
          "volume_spike": false
        },
        "change_pct": 0.2810891357355869
      },
      "news": [],
      "sentiment": 0.0,
      "atr_pct": 0.85,
      "vwap_distance": 1.71,
      "ai_recommendation": {
        "recommendation": "HOLD",
        "confidence": "LOW",
        "reasons": [
          "AI analysis (text parse)"
        ],
        "warnings": [],
        "entry_price": 300.88,
        "stop_loss": 293.36,
        "target_price": 309.91,
        "risk_reward": "3:1"
      },
      "ai_sentiment": 0.0,
      "code": "GOOGL",
      "timestamp": "2026-03-09 22:15:08"
    },
    {
      "recommendation": "HOLD",
      "confidence": "LOW",
      "entry": 260.29,
      "stop": 253.78,
      "target": 268.1,
      "rr": "3:1",
      "reasons": [
        "AI analysis (text parse)"
      ],
      "warnings": [],
      "stock_name": "Apple Inc.",
      "market_bias": "BULLISH",
      "trend_strength": "STRONG_BULLISH",
      "pattern_type": "NONE",
      "key_support": 0,
      "key_resistance": 0,
      "analysis": {
        "price": 260.29,
        "ema20": 255.83709999999996,
        "ema50": 255.83709999999996,
        "ema200": 255.83709999999996,
        "rsi": 44.60303300624428,
        "atr": 1.5511111111111089,
        "vwap": 255.37348120365232,
        "macd": {
          "macd": 0,
          "signal": 0,
          "histogram": 0,
          "trend": "NEUTRAL"
        },
        "bollinger": {
          "upper": 0,
          "middle": 0,
          "lower": 0,
          "bandwidth": 0,
          "position": 0
        },
        "stochastic": {
          "k": 50,
          "d": 50,
          "zone": "NEUTRAL"
        },
        "pivot": {
          "pivot": 255.47033333333334,
          "r1": 257.2596666666667,
          "r2": 258.8093333333333,
          "s1": 253.9206666666667,
          "s2": 252.13133333333337
        },
        "patterns": {
          "pattern": "NONE",
          "signal": "NEUTRAL",
          "volume_spike": false
        },
        "change_pct": 0.24441750420396996
      },
      "news": [],
      "sentiment": 0.0,
      "atr_pct": 0.6,
      "vwap_distance": 1.89,
      "ai_recommendation": {
        "recommendation": "HOLD",
        "confidence": "LOW",
        "reasons": [
          "AI analysis (text parse)"
        ],
        "warnings": [],
        "entry_price": 260.29,
        "stop_loss": 253.78,
        "target_price": 268.1,
        "risk_reward": "3:1"
      },
      "ai_sentiment": 0.0,
      "code": "AAPL",
      "timestamp": "2026-03-09 22:16:28"
    }
  ]
}