{
  "timestamp": "2026-04-01 12:43:58",
  "total_stocks": 1,
  "results": [
    {
      "recommendation": "HOLD",
      "confidence": "HIGH",
      "entry": 375,
      "stop": 365.62,
      "target": 386.25,
      "rr": "3:1",
      "reasons": [
        "AI analysis (text parse)"
      ],
      "warnings": [
        "Price only 0.2% from VWAP (need >1.0%)"
      ],
      "stock_name": "tsla",
      "market_bias": "BULLISH",
      "trend_strength": "STRONG_BULLISH",
      "pattern_type": "BREAKOUT",
      "key_support": 0,
      "key_resistance": 0,
      "analysis": {
        "price": 375,
        "ema20": 370.1038,
        "ema50": 370.1038,
        "ema200": 370.1038,
        "rsi": 83.67911479944681,
        "rsi_15m": 88.45128812555546,
        "atr": 4.318333333333334,
        "vwap": 374.3109982989752,
        "sma_5_5m": 374.49,
        "sma_8_5m": 374.19,
        "sma_13_5m": 0,
        "momentum_5m": "NEUTRAL",
        "sma_20_15m": 0,
        "sma_50_15m": 0,
        "trend_15m": "NEUTRAL",
        "resistance_15m": 375,
        "support_15m": 372.87,
        "macd": {
          "macd": 0,
          "signal": 0,
          "histogram": 0,
          "trend": "NEUTRAL"
        },
        "bollinger": {
          "upper": 0,
          "middle": 0,
          "lower": 0,
          "bandwidth": 0,
          "position": 0
        },
        "stochastic": {
          "k": 50,
          "d": 50,
          "zone": "NEUTRAL"
        },
        "pivot": {
          "pivot": 372.98333333333335,
          "r1": 373.7366666666667,
          "r2": 374.4033333333333,
          "s1": 372.3166666666667,
          "s2": 371.5633333333334
        },
        "patterns": {
          "pattern": "MORNING_STAR",
          "signal": "BULLISH",
          "volume_spike": false
        },
        "change_pct": 0.5173291875519358
      },
      "news": [
        {
          "title": "Tesla Faces the \u2018Couch Problem\u2019: Modern Physics Warns the Optimus Robot Will Fail and Send TSLA Stock Falling",
          "link": "https://consent.yahoo.com/v2/collectConsent?sessionId=1_cc-session_732c5159-8679-4a0e-bfd2-c0f44ebd8a30",
          "pubDate": "2026-03-20T15:24:01Z"
        },
        {
          "title": "Is\u00a0Tesla, Inc. (TSLA)\u00a0\u00a0A\u00a0Good Stock\u00a0To\u00a0Buy Now?",
          "link": "https://consent.yahoo.com/v2/collectConsent?sessionId=1_cc-session_2a25bba1-25a0-44ed-bb55-73b102b55e90",
          "pubDate": "2026-03-21T20:11:01Z"
        },
        {
          "title": "Braclays Points Out CapEx Concerns for Tesla (TSLA) Stock",
          "link": "https://consent.yahoo.com/v2/collectConsent?sessionId=1_cc-session_2e05b5c0-24d7-41ff-a7a4-718f14dd2599",
          "pubDate": "2026-03-28T15:18:45Z"
        },
        {
          "title": "Tesla\u2019s (TSLA) February Sales Figures Show Sales Growth",
          "link": "https://finance.yahoo.com/news/tesla-tsla-february-sales-figures-004432094.html",
          "pubDate": "2026-03-05T00:44:32Z"
        },
        {
          "title": "Coinbase Global Launches Stock Perpetual Futures Contracts",
          "link": "https://www.cryptoprowl.com/releases/coinbase-global-launches-stock-perpetual-futures-contracts-3924",
          "pubDate": "2026-03-20T18:24:00Z"
        },
        {
          "title": "It's Too Early To Buy the Dip in GOOG Stock Even As It Falls to Near $300",
          "link": "https://www.barchart.com/story/news/646191/it-s-too-early-to-buy-the-dip-in-goog-stock-even-as-it-falls-to-near-300",
          "pubDate": "2026-03-09T17:16:25Z"
        },
        {
          "title": "How Will Tesla Sales, TSLA Stock Be Impacted By Crude Oil Prices Due To Iran War? Gary Black Says Lays Down The Math",
          "link": "https://consent.yahoo.com/v2/collectConsent?sessionId=1_cc-session_b3b9520c-5946-49be-94e8-5f2b9f701a6f",
          "pubDate": "2026-03-17T13:30:59Z"
        },
        {
          "title": "Tesla\u2019s China-Made EV Sales Just Nearly Doubled. Should You Buy TSLA Stock Now in Hopes of an Auto Business Rebound?",
          "link": "https://consent.yahoo.com/v2/collectConsent?sessionId=1_cc-session_80dee816-c660-4055-ab31-2ce9254d4bff",
          "pubDate": "2026-03-13T21:19:33Z"
        },
        {
          "title": "Is IonQ Stock the Tesla of Quantum Computing?",
          "link": "https://www.barchart.com/story/news/540728/is-ionq-stock-the-tesla-of-quantum-computing",
          "pubDate": "2026-03-03T18:00:45Z"
        },
        {
          "title": "This Could Cut Tesla\u2019s Stock Price By 70%",
          "link": "https://247wallst.com/investing/2026/03/24/this-could-cut-teslas-stock-price-by-70/",
          "pubDate": "2026-03-24T12:30:28Z"
        }
      ],
      "sentiment": -0.4,
      "atr_pct": 1.15,
      "vwap_distance": 0.18,
      "ai_recommendation": {
        "recommendation": "HOLD",
        "confidence": "HIGH",
        "reasons": [
          "AI analysis (text parse)"
        ],
        "warnings": [],
        "entry_price": 375,
        "stop_loss": 365.62,
        "target_price": 386.25,
        "risk_reward": "3:1"
      },
      "ai_sentiment": -0.4,
      "code": "tsla",
      "timestamp": "2026-04-01 12:43:58"
    }
  ]
}