{
  "timestamp": "2026-03-30 11:00:00",
  "results": [
    {
      "code": "568",
      "stock_name": "568",
      "recommendation": "SELL",
      "entry": 10.37,
      "stop": 10.68,
      "target": 10.06,
      "confidence": "MEDIUM",
      "timestamp": "2026-03-30 11:00:00",
      "analysis": {
        "price": 10.369999885559082,
        "ema20": 10.400763257846952,
        "ema50": 10.628510852467928,
        "rsi": 53.66972396795302,
        "atr": 0.3157141549246652,
        "vwap": 10.759291307217529
      }
    }
  ]
}