{
  "timestamp": "2026-03-19 11:00:00",
  "results": [
    {
      "code": "3690",
      "stock_name": "3690",
      "recommendation": "BUY",
      "entry": 81.0,
      "stop": 78.57,
      "target": 83.43,
      "confidence": "MEDIUM",
      "timestamp": "2026-03-19 11:00:00",
      "analysis": {
        "price": 81.0,
        "ema20": 79.9839953075696,
        "ema50": 78.92731788905671,
        "rsi": 46.46466514695433,
        "atr": 0.8785716465541294,
        "vwap": 78.94897597705979
      }
    }
  ]
}