{
  "timestamp": "2026-03-22 11:00:00",
  "results": [
    {
      "code": "3317",
      "stock_name": "3317",
      "recommendation": "BUY",
      "entry": 147.0,
      "stop": 142.59,
      "target": 151.41,
      "confidence": "MEDIUM",
      "timestamp": "2026-03-22 11:00:00",
      "analysis": {
        "price": 147.0,
        "ema20": 143.067722954213,
        "ema50": 134.16789693810236,
        "rsi": 45.454527439427174,
        "atr": 7.092857360839844,
        "vwap": 133.5950699552263
      }
    }
  ]
}