{
  "timestamp": "2026-03-18 11:00:00",
  "results": [
    {
      "code": "9992",
      "stock_name": "9992",
      "recommendation": "BUY",
      "entry": 221.2,
      "stop": 214.56,
      "target": 227.84,
      "confidence": "MEDIUM",
      "timestamp": "2026-03-18 11:00:00",
      "analysis": {
        "price": 221.1999969482422,
        "ema20": 213.77518508729568,
        "ema50": 211.31127408206677,
        "rsi": 69.8529490137604,
        "atr": 3.0857151576450894,
        "vwap": 217.72031720732278
      }
    }
  ]
}