{
  "timestamp": "2026-03-24 11:00:00",
  "results": [
    {
      "code": "568",
      "stock_name": "568",
      "recommendation": "BUY",
      "entry": 11.25,
      "stop": 10.91,
      "target": 11.59,
      "confidence": "MEDIUM",
      "timestamp": "2026-03-24 11:00:00",
      "analysis": {
        "price": 11.25,
        "ema20": 11.427647674584826,
        "ema50": 11.116270944520569,
        "rsi": 49.59999084472656,
        "atr": 0.37071425574166433,
        "vwap": 10.548931199162459
      }
    }
  ]
}